{"version": "0.1.3", "img_width": 1524, "img_height": 1200, "blocks": [{"box": [1376, 120, 1452, 215], "vertical": true, "font_size": 25, "lines_coords": [[[1424.0, 120.0], [1451.0, 120.0], [1452.0, 215.0], [1425.0, 215.0]], [[1397.0, 120.0], [1424.0, 120.0], [1421.0, 214.0], [1394.0, 214.0]], [[1376.0, 122.0], [1398.0, 122.0], [1398.0, 181.0], [1376.0, 181.0]]], "lines": ["シュシュは", "頭のいい犬", "だから"]}, {"box": [1076, 114, 1183, 247], "vertical": true, "font_size": 24, "lines_coords": [[[1147.0, 114.0], [1183.0, 117.0], [1177.0, 186.0], [1141.0, 183.0]], [[1125.0, 123.0], [1145.0, 123.0], [1145.0, 247.0], [1125.0, 247.0]], [[1095.0, 120.0], [1117.0, 120.0], [1119.0, 230.0], [1096.0, 230.0]], [[1076.0, 125.0], [1092.0, 125.0], [1092.0, 212.0], [1076.0, 212.0]]], "lines": ["主人が", "死んだ事くらい", "とうに知って", "おるだろう"]}, {"box": [1363, 457, 1465, 538], "vertical": true, "font_size": 29, "lines_coords": [[[1431.0, 461.0], [1461.0, 457.0], [1465.0, 500.0], [1436.0, 504.0]], [[1412.0, 460.0], [1437.0, 460.0], [1437.0, 538.0], [1412.0, 538.0]], [[1381.0, 458.0], [1418.0, 458.0], [1418.0, 507.0], [1381.0, 507.0]], [[1363.0, 458.0], [1388.0, 458.0], [1388.0, 537.0], [1363.0, 537.0]]], "lines": ["じゃ", "どうして", "店番", "なんて．．．"]}, {"box": [1093, 460, 1150, 538], "vertical": true, "font_size": 30, "lines_coords": [[[1117.0, 460.0], [1150.0, 460.0], [1150.0, 524.0], [1117.0, 524.0]], [[1093.0, 463.0], [1120.0, 463.0], [1120.0, 538.0], [1093.0, 538.0]]], "lines": ["きっと", "この店は"]}, {"box": [820, 303, 837, 375], "vertical": true, "font_size": 17, "lines_coords": [[[820.0, 303.0], [837.0, 303.0], [837.0, 375.0], [820.0, 375.0]]], "lines": ["．．．．．．"]}, {"box": [823, 486, 908, 595], "vertical": true, "font_size": 26, "lines_coords": [[[882.0, 491.0], [907.0, 491.0], [907.0, 592.0], [882.0, 592.0]], [[851.0, 486.0], [884.0, 486.0], [884.0, 558.0], [851.0, 558.0]], [[824.0, 491.0], [845.0, 491.0], [845.0, 595.0], [824.0, 595.0]]], "lines": ["シュシュに", "とって", "宝なんじゃ"]}, {"box": [1363, 890, 1458, 1022], "vertical": true, "font_size": 27, "lines_coords": [[[1424.0, 890.0], [1451.0, 890.0], [1448.0, 1022.0], [1421.0, 1022.0]], [[1391.0, 890.0], [1416.0, 890.0], [1416.0, 1004.0], [1391.0, 1004.0]], [[1363.0, 890.0], [1391.0, 890.0], [1391.0, 961.0], [1363.0, 961.0]]], "lines": ["大好きだった", "主人の形身", "だから"]}, {"box": [803, 902, 934, 1063], "vertical": true, "font_size": 32, "lines_coords": [[[901.0, 903.0], [934.0, 903.0], [934.0, 978.0], [901.0, 978.0]], [[864.0, 902.0], [906.0, 902.0], [906.0, 961.0], [864.0, 961.0]], [[837.0, 906.0], [863.0, 906.0], [866.0, 1063.0], [840.0, 1063.0]], [[803.0, 908.0], [828.0, 908.0], [831.0, 1022.0], [806.0, 1022.0]]], "lines": ["それを", "守り", "続けとるのだと", "わしは思う"]}, {"box": [620, 129, 700, 275], "vertical": true, "font_size": 24, "lines_coords": [[[669.0, 129.0], [700.0, 129.0], [700.0, 245.0], [669.0, 245.0]], [[645.0, 132.0], [666.0, 132.0], [666.0, 266.0], [645.0, 266.0]], [[622.0, 131.0], [642.0, 131.0], [641.0, 275.0], [620.0, 275.0]]], "lines": ["困ったもんよ", "わしが何度、避難", "させようとしても"]}, {"box": [241, 120, 348, 391], "vertical": true, "font_size": 21, "lines_coords": [[[319.0, 122.0], [340.0, 122.0], [340.0, 229.0], [319.0, 229.0]], [[309.0, 302.0], [334.0, 302.0], [334.0, 384.0], [309.0, 384.0]], [[293.0, 122.0], [314.0, 122.0], [314.0, 245.0], [293.0, 245.0]], [[284.0, 300.0], [306.0, 300.0], [308.0, 384.0], [285.0, 384.0]], [[269.0, 122.0], [290.0, 122.0], [290.0, 195.0], [269.0, 195.0]], [[258.0, 300.0], [281.0, 299.0], [284.0, 369.0], [261.0, 370.0]], [[242.0, 302.0], [258.0, 302.0], [258.0, 390.0], [242.0, 390.0]]], "lines": ["一歩たりとも", "放っときゃ", "ここを動こうと", "餓死しても", "せんのだ", "居続ける", "つもりらしい"]}, {"box": [359, 457, 684, 610], "vertical": false, "font_size": 153, "lines_coords": [[[359.0, 457.0], [684.0, 457.0], [684.0, 610.0], [359.0, 610.0]]], "lines": ["オオイ"]}, {"box": [191, 476, 285, 591], "vertical": true, "font_size": 31, "lines_coords": [[[247.0, 476.0], [285.0, 476.0], [285.0, 553.0], [247.0, 553.0]], [[218.0, 480.0], [245.0, 480.0], [245.0, 591.0], [218.0, 591.0]], [[191.0, 477.0], [218.0, 477.0], [218.0, 547.0], [191.0, 547.0]]], "lines": ["な．．．何", "この雄叫び", "．．．！！"]}, {"box": [53, 332, 69, 404], "vertical": true, "font_size": 16, "lines_coords": [[[53.0, 332.0], [69.0, 332.0], [69.0, 404.0], [53.0, 404.0]]], "lines": ["．．．"]}, {"box": [26, 471, 142, 608], "vertical": true, "font_size": 26, "lines_coords": [[[116.0, 473.0], [141.0, 473.0], [141.0, 585.0], [116.0, 585.0]], [[87.0, 471.0], [113.0, 471.0], [116.0, 608.0], [90.0, 608.0]], [[55.0, 474.0], [80.0, 474.0], [80.0, 598.0], [55.0, 598.0]], [[26.0, 474.0], [52.0, 474.0], [52.0, 598.0], [26.0, 598.0]]], "lines": ["こ．．．こりゃ", "あいつじゃ！！", "〝猛獣使いの", "モージムじゃ"]}, {"box": [322, 750, 351, 803], "vertical": true, "font_size": 29, "lines_coords": [[[322.0, 750.0], [351.0, 750.0], [351.0, 803.0], [322.0, 803.0]]], "lines": ["え！？"]}, {"box": [601, 863, 695, 949], "vertical": true, "font_size": 23, "lines_coords": [[[668.0, 866.0], [695.0, 866.0], [695.0, 926.0], [668.0, 926.0]], [[647.0, 866.0], [675.0, 866.0], [675.0, 926.0], [647.0, 926.0]], [[626.0, 867.0], [647.0, 867.0], [647.0, 949.0], [626.0, 949.0]], [[616.0, 863.0], [631.0, 878.0], [616.0, 893.0], [601.0, 878.0]]], "lines": ["あーあ", "なんか", "来ちまった", "＞"]}, {"box": [302, 870, 400, 958], "vertical": true, "font_size": 35, "lines_coords": [[[361.0, 873.0], [400.0, 873.0], [400.0, 958.0], [361.0, 958.0]], [[337.0, 876.0], [366.0, 876.0], [366.0, 926.0], [337.0, 926.0]], [[302.0, 870.0], [339.0, 870.0], [339.0, 954.0], [302.0, 954.0]]], "lines": ["逃げろ", "オー", "ーっ！！！"]}, {"box": [403, 1076, 508, 1158], "vertical": false, "font_size": 82, "lines_coords": [[[403.0, 1076.0], [508.0, 1076.0], [508.0, 1158.0], [403.0, 1158.0]]], "lines": ["鍵返せよお前ェ"]}, {"box": [278, 1112, 308, 1159], "vertical": true, "font_size": 30, "lines_coords": [[[278.0, 1112.0], [308.0, 1112.0], [308.0, 1159.0], [278.0, 1159.0]]], "lines": ["ガウ"]}]}