{"version": "0.1.3", "img_width": 1064, "img_height": 1600, "blocks": [{"box": [280, 68, 304, 126], "vertical": true, "font_size": 24, "lines_coords": [[[280.0, 68.0], [304.0, 68.0], [304.0, 126.0], [280.0, 126.0]]], "lines": ["！"]}, {"box": [557, 1345, 648, 1476], "vertical": true, "font_size": 26, "lines_coords": [[[617.0, 1345.0], [648.0, 1345.0], [648.0, 1400.0], [617.0, 1400.0]], [[587.0, 1345.0], [614.0, 1345.0], [610.0, 1476.0], [584.0, 1476.0]], [[557.0, 1420.0], [579.0, 1420.0], [579.0, 1476.0], [557.0, 1476.0]]], "lines": ["くっ", "落とされた", "．．．"]}]}