{"version": "0.1.3", "img_width": 1084, "img_height": 1600, "blocks": [{"box": [940, 130, 976, 264], "vertical": true, "font_size": 26, "lines_coords": [[[940.0, 137.0], [966.0, 137.0], [966.0, 264.0], [940.0, 264.0]]], "lines": ["．．．．．．趙相明"]}, {"box": [454, 126, 478, 230], "vertical": true, "font_size": 22, "lines_coords": [[[454.0, 128.0], [476.0, 128.0], [476.0, 229.0], [454.0, 229.0]]], "lines": ["ああ．．．．．"]}, {"box": [76, 126, 178, 278], "vertical": true, "font_size": 30, "lines_coords": [[[135.0, 126.0], [170.0, 126.0], [170.0, 209.0], [135.0, 209.0]], [[109.0, 129.0], [135.0, 129.0], [135.0, 278.0], [109.0, 278.0]], [[76.0, 129.0], [104.0, 129.0], [104.0, 210.0], [76.0, 210.0]]], "lines": ["哲夫の", "ボディガード", "ね．．．．．"]}, {"box": [939, 613, 974, 742], "vertical": true, "font_size": 35, "lines_coords": [[[939.0, 613.0], [974.0, 613.0], [974.0, 742.0], [939.0, 742.0]]], "lines": ["．．．．．．で"]}, {"box": [581, 602, 613, 764], "vertical": true, "font_size": 31, "lines_coords": [[[581.0, 604.0], [612.0, 604.0], [612.0, 764.0], [581.0, 764.0]]], "lines": ["悔しいの？"]}, {"box": [101, 1330, 158, 1455], "vertical": true, "font_size": 24, "lines_coords": [[[131.0, 1331.0], [157.0, 1331.0], [157.0, 1454.0], [131.0, 1454.0]], [[101.0, 1331.0], [123.0, 1331.0], [123.0, 1431.0], [101.0, 1431.0]]], "lines": ["山口俊夫が", "死んでた"]}]}