{"version": "0.1.3", "img_width": 1104, "img_height": 1600, "blocks": [{"box": [891, 123, 986, 231], "vertical": true, "font_size": 31, "lines_coords": [[[957.0, 123.0], [985.0, 123.0], [986.0, 228.0], [958.0, 228.0]], [[925.0, 123.0], [954.0, 123.0], [955.0, 231.0], [927.0, 231.0]], [[891.0, 123.0], [927.0, 123.0], [927.0, 182.0], [891.0, 182.0]]], "lines": ["これまで", "３回対戦", "して"]}, {"box": [544, 128, 669, 285], "vertical": true, "font_size": 25, "lines_coords": [[[646.0, 131.0], [668.0, 131.0], [668.0, 256.0], [646.0, 256.0]], [[613.0, 132.0], [635.0, 132.0], [635.0, 257.0], [613.0, 257.0]], [[579.0, 129.0], [605.0, 129.0], [605.0, 285.0], [579.0, 285.0]], [[544.0, 129.0], [573.0, 128.0], [576.0, 209.0], [548.0, 210.0]]], "lines": ["３回ともに", "田宮さんが", "負けてるんだ", "よな．．．"]}, {"box": [424, 126, 513, 282], "vertical": true, "font_size": 27, "lines_coords": [[[484.0, 126.0], [510.0, 126.0], [513.0, 243.0], [487.0, 243.0]], [[452.0, 126.0], [479.0, 126.0], [482.0, 282.0], [455.0, 282.0]], [[424.0, 128.0], [451.0, 128.0], [451.0, 231.0], [424.0, 231.0]]], "lines": ["ただ今日", "小笠原選手も", "ここまで"]}, {"box": [101, 557, 224, 740], "vertical": true, "font_size": 27, "lines_coords": [[[193.0, 557.0], [220.0, 557.0], [223.0, 715.0], [196.0, 715.0]], [[163.0, 559.0], [190.0, 559.0], [190.0, 700.0], [163.0, 700.0]], [[129.0, 559.0], [157.0, 559.0], [159.0, 689.0], [131.0, 689.0]], [[101.0, 560.0], [128.0, 560.0], [128.0, 740.0], [101.0, 740.0]]], "lines": ["人が変わった", "様にオール", "一本勝ちで", "上がって来てる"]}, {"box": [836, 787, 994, 967], "vertical": true, "font_size": 27, "lines_coords": [[[968.0, 787.0], [994.0, 787.0], [994.0, 939.0], [968.0, 939.0]], [[938.0, 790.0], [960.0, 790.0], [960.0, 965.0], [938.0, 965.0]], [[904.0, 789.0], [930.0, 789.0], [930.0, 967.0], [904.0, 967.0]], [[871.0, 790.0], [897.0, 790.0], [899.0, 965.0], [872.0, 965.0]], [[836.0, 787.0], [871.0, 787.0], [871.0, 893.0], [836.0, 893.0]]], "lines": ["その小笠原に", "ルールが違えど", "メグルが２回も", "一本勝ちしてる", "のが．．．"]}, {"box": [752, 828, 811, 985], "vertical": true, "font_size": 27, "lines_coords": [[[777.0, 828.0], [811.0, 828.0], [811.0, 912.0], [777.0, 912.0]], [[752.0, 832.0], [774.0, 832.0], [774.0, 985.0], [752.0, 985.0]]], "lines": ["未だに", "信じられんが"]}, {"box": [677, 904, 708, 1032], "vertical": true, "font_size": 28, "lines_coords": [[[680.0, 904.0], [708.0, 904.0], [705.0, 1032.0], [677.0, 1032.0]]], "lines": ["えっえっ"]}, {"box": [382, 793, 507, 925], "vertical": true, "font_size": 26, "lines_coords": [[[476.0, 795.0], [504.0, 795.0], [507.0, 925.0], [479.0, 925.0]], [[448.0, 793.0], [474.0, 793.0], [474.0, 923.0], [448.0, 923.0]], [[420.0, 796.0], [441.0, 796.0], [441.0, 895.0], [420.0, 895.0]], [[382.0, 793.0], [409.0, 793.0], [412.0, 898.0], [385.0, 898.0]]], "lines": ["いいかげん", "こいつには", "キッチリ", "勝たんと"]}, {"box": [178, 786, 299, 915], "vertical": true, "font_size": 22, "lines_coords": [[[271.0, 787.0], [293.0, 787.0], [293.0, 889.0], [271.0, 889.0]], [[242.0, 787.0], [263.0, 787.0], [263.0, 912.0], [242.0, 912.0]], [[210.0, 787.0], [232.0, 787.0], [232.0, 914.0], [210.0, 914.0]], [[178.0, 789.0], [199.0, 789.0], [199.0, 915.0], [178.0, 915.0]]], "lines": ["俺の柔術", "キャリアの", "汚点になり", "かねん．．．．．．"]}]}