{"version": "0.1.3", "img_width": 1094, "img_height": 1600, "blocks": [{"box": [304, 135, 337, 256], "vertical": true, "font_size": 33, "lines_coords": [[[304.0, 135.0], [337.0, 135.0], [337.0, 256.0], [304.0, 256.0]]], "lines": ["ファイッ"]}, {"box": [881, 670, 992, 812], "vertical": true, "font_size": 26, "lines_coords": [[[965.0, 670.0], [992.0, 670.0], [992.0, 812.0], [965.0, 812.0]], [[936.0, 670.0], [962.0, 670.0], [962.0, 768.0], [936.0, 768.0]], [[906.0, 670.0], [933.0, 670.0], [933.0, 765.0], [906.0, 765.0]], [[881.0, 671.0], [903.0, 671.0], [903.0, 787.0], [881.0, 787.0]]], "lines": ["上になっても", "また変な", "ガードに", "捕まって．．．"]}, {"box": [592, 673, 683, 781], "vertical": true, "font_size": 29, "lines_coords": [[[656.0, 676.0], [682.0, 676.0], [682.0, 781.0], [656.0, 781.0]], [[620.0, 673.0], [653.0, 673.0], [653.0, 756.0], [620.0, 756.0]], [[592.0, 673.0], [620.0, 673.0], [620.0, 753.0], [592.0, 753.0]]], "lines": ["ペースを", "握られ", "る．．．．．"]}, {"box": [294, 735, 315, 777], "vertical": true, "font_size": 21, "lines_coords": [[[294.0, 735.0], [315.0, 735.0], [315.0, 777.0], [294.0, 777.0]]], "lines": ["！"]}, {"box": [961, 1106, 984, 1209], "vertical": true, "font_size": 22, "lines_coords": [[[961.0, 1107.0], [983.0, 1107.0], [983.0, 1209.0], [961.0, 1209.0]]], "lines": ["だったら"]}, {"box": [792, 1109, 822, 1185], "vertical": true, "font_size": 30, "lines_coords": [[[792.0, 1109.0], [822.0, 1109.0], [822.0, 1185.0], [792.0, 1185.0]]], "lines": ["よーし"]}]}