{"version": "0.1.3", "img_width": 1097, "img_height": 1600, "blocks": [{"box": [531, 121, 589, 274], "vertical": true, "font_size": 25, "lines_coords": [[[561.0, 121.0], [589.0, 121.0], [589.0, 225.0], [561.0, 225.0]], [[531.0, 125.0], [553.0, 125.0], [553.0, 271.0], [531.0, 271.0]]], "lines": ["マウント", "いただきや！！"]}, {"box": [230, 100, 251, 140], "vertical": true, "font_size": 21, "lines_coords": [[[230.0, 100.0], [251.0, 100.0], [251.0, 140.0], [230.0, 140.0]]], "lines": ["！"]}, {"box": [629, 1204, 697, 1326], "vertical": true, "font_size": 28, "lines_coords": [[[668.0, 1206.0], [696.0, 1206.0], [696.0, 1326.0], [668.0, 1326.0]], [[629.0, 1204.0], [657.0, 1204.0], [657.0, 1325.0], [629.0, 1325.0]]], "lines": ["室井さん", "立てる！！"]}, {"box": [490, 1204, 518, 1345], "vertical": true, "font_size": 28, "lines_coords": [[[490.0, 1204.0], [518.0, 1204.0], [518.0, 1345.0], [490.0, 1345.0]]], "lines": ["チャンス！！"]}, {"box": [106, 1196, 181, 1321], "vertical": true, "font_size": 35, "lines_coords": [[[150.0, 1201.0], [178.0, 1201.0], [178.0, 1321.0], [150.0, 1321.0]], [[106.0, 1196.0], [148.0, 1196.0], [148.0, 1239.0], [106.0, 1239.0]]], "lines": ["逃がすか", "！！"]}]}