{"version": "0.1.3", "img_width": 1350, "img_height": 1920, "blocks": [{"box": [315, 858, 579, 885], "vertical": false, "font_size": 27, "lines_coords": [[[315.0, 858.0], [579.0, 858.0], [579.0, 885.0], [315.0, 885.0]]], "lines": ["第二幕開墾"]}, {"box": [406, 579, 658, 600], "vertical": false, "font_size": 19, "lines_coords": [[[613.0, 579.0], [658.0, 583.0], [656.0, 598.0], [611.0, 594.0]], [[500.0, 579.0], [611.0, 579.0], [611.0, 600.0], [500.0, 600.0]], [[406.0, 581.0], [423.0, 581.0], [423.0, 598.0], [406.0, 598.0]]], "lines": ["．．．", "あ、ああ．．．", "．．．"]}, {"box": [521, 504, 866, 538], "vertical": false, "font_size": 19, "lines_coords": [[[851.0, 510.0], [866.0, 523.0], [855.0, 534.0], [841.0, 519.0]], [[521.0, 504.0], [761.0, 506.0], [761.0, 538.0], [521.0, 536.0]]], "lines": ["．．．", "お客様のお"]}, {"box": [313, 743, 986, 791], "vertical": false, "font_size": 24, "lines_coords": [[[313.0, 751.0], [581.0, 751.0], [581.0, 778.0], [313.0, 778.0]], [[864.0, 755.0], [963.0, 755.0], [963.0, 776.0], [864.0, 776.0]]], "lines": ["第一基地", "００三"]}, {"box": [810, 858, 967, 883], "vertical": false, "font_size": 25, "lines_coords": [[[810.0, 858.0], [967.0, 858.0], [967.0, 883.0], [810.0, 883.0]]], "lines": ["．．．。○三七"]}, {"box": [946, 508, 976, 600], "vertical": true, "font_size": 26, "lines_coords": [[[946.0, 508.0], [973.0, 508.0], [976.0, 600.0], [950.0, 600.0]]], "lines": ["アー次"]}, {"box": [309, 961, 618, 993], "vertical": false, "font_size": 32, "lines_coords": [[[309.0, 961.0], [618.0, 961.0], [618.0, 993.0], [309.0, 993.0]]], "lines": ["第三幕、結城．．．"]}, {"box": [313, 1068, 620, 1095], "vertical": false, "font_size": 27, "lines_coords": [[[313.0, 1068.0], [620.0, 1068.0], [620.0, 1095.0], [313.0, 1095.0]]], "lines": ["第四幕入浴・"]}, {"box": [309, 1168, 628, 1203], "vertical": false, "font_size": 32, "lines_coords": [[[309.0, 1168.0], [628.0, 1171.0], [628.0, 1203.0], [309.0, 1200.0]]], "lines": ["第五幕講見．．．"]}, {"box": [315, 1321, 744, 1348], "vertical": false, "font_size": 27, "lines_coords": [[[315.0, 1321.0], [744.0, 1321.0], [744.0, 1348.0], [315.0, 1348.0]]], "lines": ["書き下ろし小説現代小町苦労調"]}, {"box": [834, 1177, 965, 1198], "vertical": false, "font_size": 21, "lines_coords": [[[834.0, 1177.0], [965.0, 1177.0], [965.0, 1198.0], [834.0, 1198.0]]], "lines": ["・一三七"]}]}