{"version": "0.1.3", "img_width": 1112, "img_height": 1600, "blocks": [{"box": [716, 828, 779, 930], "vertical": true, "font_size": 42, "lines_coords": [[[716.0, 839.0], [757.0, 828.0], [779.0, 912.0], [738.0, 923.0]]], "lines": ["ミュッ"]}, {"box": [563, 785, 616, 884], "vertical": true, "font_size": 53, "lines_coords": [[[563.0, 785.0], [616.0, 785.0], [616.0, 884.0], [563.0, 884.0]]], "lines": ["シュッ"]}, {"box": [721, 1173, 776, 1254], "vertical": true, "font_size": 35, "lines_coords": [[[741.0, 1173.0], [776.0, 1173.0], [776.0, 1254.0], [741.0, 1254.0]]], "lines": ["ふーん"]}, {"box": [139, 1428, 201, 1531], "vertical": true, "font_size": 31, "lines_coords": [[[165.0, 1428.0], [201.0, 1428.0], [201.0, 1509.0], [165.0, 1509.0]], [[139.0, 1429.0], [165.0, 1429.0], [165.0, 1531.0], [139.0, 1531.0]]], "lines": ["ジャブ", "ねぇ．．．．．．"]}]}