{"version": "0.1.3", "img_width": 1094, "img_height": 1600, "blocks": [{"box": [863, 613, 978, 767], "vertical": true, "font_size": 25, "lines_coords": [[[953.0, 615.0], [975.0, 615.0], [975.0, 742.0], [953.0, 742.0]], [[918.0, 614.0], [947.0, 614.0], [947.0, 717.0], [918.0, 717.0]], [[887.0, 614.0], [911.0, 614.0], [912.0, 767.0], [889.0, 767.0]]], "lines": ["田宮さんが", "立ち技で", "あおられてる"]}, {"box": [559, 609, 645, 707], "vertical": true, "font_size": 28, "lines_coords": [[[618.0, 609.0], [645.0, 609.0], [645.0, 707.0], [618.0, 707.0]], [[589.0, 609.0], [617.0, 609.0], [617.0, 707.0], [589.0, 707.0]], [[559.0, 609.0], [587.0, 609.0], [587.0, 685.0], [559.0, 685.0]]], "lines": ["ちょっと", "すごいな", "あの子"]}, {"box": [129, 609, 159, 713], "vertical": true, "font_size": 28, "lines_coords": [[[129.0, 609.0], [157.0, 609.0], [159.0, 712.0], [131.0, 712.0]]], "lines": ["だが．．．"]}, {"box": [361, 1025, 449, 1179], "vertical": true, "font_size": 24, "lines_coords": [[[425.0, 1026.0], [446.0, 1026.0], [446.0, 1153.0], [425.0, 1153.0]], [[389.0, 1025.0], [417.0, 1025.0], [418.0, 1179.0], [390.0, 1179.0]], [[361.0, 1026.0], [384.0, 1026.0], [384.0, 1101.0], [361.0, 1101.0]]], "lines": ["引き込みに", "面くらってる", "な．．．"]}, {"box": [196, 1020, 292, 1128], "vertical": true, "font_size": 30, "lines_coords": [[[256.0, 1020.0], [292.0, 1020.0], [292.0, 1081.0], [256.0, 1081.0]], [[228.0, 1021.0], [256.0, 1021.0], [257.0, 1128.0], [229.0, 1128.0]], [[196.0, 1023.0], [223.0, 1023.0], [223.0, 1126.0], [196.0, 1126.0]]], "lines": ["まあ", "柔道では", "反則だし"]}]}