{"version": "0.1.3", "img_width": 1094, "img_height": 1600, "blocks": [{"box": [853, 781, 929, 879], "vertical": true, "font_size": 38, "lines_coords": [[[886.0, 781.0], [929.0, 781.0], [929.0, 853.0], [886.0, 853.0]], [[853.0, 782.0], [887.0, 782.0], [887.0, 879.0], [853.0, 879.0]]], "lines": ["何だ", "何だ！？"]}, {"box": [317, 778, 386, 901], "vertical": true, "font_size": 30, "lines_coords": [[[353.0, 778.0], [386.0, 778.0], [386.0, 873.0], [353.0, 873.0]], [[317.0, 779.0], [345.0, 779.0], [345.0, 901.0], [317.0, 901.0]]], "lines": ["お前ら", "止めろ！"]}, {"box": [711, 1326, 739, 1462], "vertical": true, "font_size": 26, "lines_coords": [[[711.0, 1326.0], [737.0, 1326.0], [737.0, 1462.0], [711.0, 1462.0]]], "lines": ["ケンカか？"]}, {"box": [293, 1310, 366, 1462], "vertical": true, "font_size": 28, "lines_coords": [[[334.0, 1312.0], [362.0, 1312.0], [362.0, 1460.0], [334.0, 1460.0]], [[296.0, 1310.0], [325.0, 1310.0], [321.0, 1434.0], [293.0, 1434.0]]], "lines": ["出場停止に", "なるぞ！"]}]}