{"version": "0.1.3", "img_width": 1524, "img_height": 1200, "blocks": [{"box": [1418, 81, 1484, 403], "vertical": true, "font_size": 61, "lines_coords": [[[1418.0, 81.0], [1479.0, 81.0], [1479.0, 403.0], [1418.0, 403.0]]], "lines": ["分解すんな！！！"]}, {"box": [1416, 516, 1449, 583], "vertical": true, "font_size": 25, "lines_coords": [[[1416.0, 516.0], [1449.0, 516.0], [1449.0, 583.0], [1416.0, 583.0]]], "lines": ["おい．．．"]}, {"box": [1305, 519, 1393, 622], "vertical": true, "font_size": 25, "lines_coords": [[[1366.0, 519.0], [1393.0, 519.0], [1393.0, 608.0], [1366.0, 608.0]], [[1342.0, 519.0], [1367.0, 519.0], [1367.0, 608.0], [1342.0, 608.0]], [[1318.0, 521.0], [1343.0, 521.0], [1343.0, 608.0], [1318.0, 608.0]], [[1305.0, 522.0], [1321.0, 522.0], [1321.0, 622.0], [1305.0, 622.0]]], "lines": ["もしかして笑っちゃう", "船長．．．少し", "押されぎみ", "じゃねェか？"]}, {"box": [1174, 519, 1250, 594], "vertical": true, "font_size": 27, "lines_coords": [[[1218.0, 519.0], [1250.0, 519.0], [1250.0, 562.0], [1218.0, 562.0]], [[1196.0, 519.0], [1223.0, 519.0], [1223.0, 594.0], [1196.0, 594.0]], [[1174.0, 522.0], [1195.0, 522.0], [1195.0, 592.0], [1174.0, 592.0]]], "lines": ["ば．．．", "ばかな事", "言うな！"]}, {"box": [1016, 509, 1129, 613], "vertical": true, "font_size": 20, "lines_coords": [[[1108.0, 510.0], [1129.0, 510.0], [1129.0, 611.0], [1108.0, 611.0]], [[1083.0, 509.0], [1104.0, 509.0], [1104.0, 595.0], [1083.0, 595.0]], [[1064.0, 512.0], [1080.0, 512.0], [1080.0, 610.0], [1064.0, 610.0]], [[1037.0, 509.0], [1059.0, 509.0], [1059.0, 564.0], [1037.0, 564.0]], [[1016.0, 509.0], [1037.0, 509.0], [1040.0, 613.0], [1019.0, 613.0]]], "lines": ["バギー船長が", "負けるか！", "船長の本当の", "怖さは", "これからだ！"]}, {"box": [831, 285, 881, 430], "vertical": true, "font_size": 50, "lines_coords": [[[831.0, 290.0], [881.0, 290.0], [881.0, 430.0], [831.0, 430.0]]], "lines": ["んぼ！！！"]}, {"box": [936, 525, 956, 619], "vertical": true, "font_size": 20, "lines_coords": [[[936.0, 525.0], [956.0, 525.0], [956.0, 619.0], [936.0, 619.0]]], "lines": ["のはずだ！！"]}, {"box": [846, 511, 866, 604], "vertical": true, "font_size": 20, "lines_coords": [[[846.0, 511.0], [866.0, 511.0], [866.0, 604.0], [846.0, 604.0]]], "lines": ["それはわかりません！！"]}, {"box": [1432, 847, 1452, 919], "vertical": true, "font_size": 20, "lines_coords": [[[1432.0, 847.0], [1452.0, 847.0], [1452.0, 919.0], [1432.0, 919.0]]], "lines": ["わあわああもあの"]}, {"box": [1238, 854, 1289, 970], "vertical": true, "font_size": 21, "lines_coords": [[[1266.0, 857.0], [1287.0, 857.0], [1287.0, 970.0], [1266.0, 970.0]], [[1239.0, 854.0], [1260.0, 854.0], [1259.0, 970.0], [1238.0, 970.0]]], "lines": ["いがんいかん", "見とれてたわ"]}, {"box": [823, 869, 924, 1031], "vertical": true, "font_size": 26, "lines_coords": [[[887.0, 869.0], [918.0, 869.0], [918.0, 1031.0], [887.0, 1031.0]], [[855.0, 869.0], [881.0, 869.0], [881.0, 984.0], [855.0, 984.0]], [[823.0, 870.0], [843.0, 870.0], [843.0, 1006.0], [823.0, 1006.0]]], "lines": ["私は早く小屋の", "宝を盗んで", "逃げなきゃ！！"]}, {"box": [619, 69, 689, 165], "vertical": true, "font_size": 26, "lines_coords": [[[653.0, 72.0], [680.0, 72.0], [680.0, 165.0], [653.0, 165.0]], [[622.0, 69.0], [647.0, 69.0], [644.0, 165.0], [619.0, 165.0]]], "lines": ["町民達の", "避難所ー"]}, {"box": [440, 69, 494, 186], "vertical": true, "font_size": 27, "lines_coords": [[[465.0, 69.0], [494.0, 69.0], [491.0, 165.0], [462.0, 165.0]], [[440.0, 71.0], [465.0, 71.0], [465.0, 186.0], [440.0, 186.0]]], "lines": ["やっぱり", "おかしい！！"]}, {"box": [59, 77, 142, 212], "vertical": true, "font_size": 22, "lines_coords": [[[111.0, 77.0], [136.0, 77.0], [136.0, 195.0], [111.0, 195.0]], [[84.0, 77.0], [107.0, 77.0], [108.0, 195.0], [86.0, 195.0]], [[59.0, 78.0], [78.0, 78.0], [78.0, 212.0], [59.0, 212.0]]], "lines": ["こんなに長く", "町長が帰って", "来ないなんて！"]}, {"box": [52, 273, 68, 319], "vertical": true, "font_size": 16, "lines_coords": [[[52.0, 273.0], [68.0, 273.0], [68.0, 319.0], [52.0, 319.0]]], "lines": ["それはあまり"]}, {"box": [668, 454, 689, 567], "vertical": true, "font_size": 21, "lines_coords": [[[668.0, 454.0], [689.0, 454.0], [689.0, 567.0], [668.0, 567.0]]], "lines": ["あやつめ．．．"]}, {"box": [370, 443, 461, 583], "vertical": true, "font_size": 29, "lines_coords": [[[421.0, 445.0], [453.0, 443.0], [456.0, 537.0], [424.0, 538.0]], [[389.0, 445.0], [422.0, 445.0], [422.0, 521.0], [389.0, 521.0]], [[370.0, 446.0], [392.0, 446.0], [394.0, 582.0], [372.0, 582.0]]], "lines": ["町民達に", "心配を", "かけおって．．．"]}, {"box": [227, 446, 322, 537], "vertical": true, "font_size": 26, "lines_coords": [[[290.0, 446.0], [322.0, 446.0], [322.0, 524.0], [290.0, 524.0]], [[266.0, 446.0], [297.0, 446.0], [297.0, 525.0], [266.0, 525.0]], [[247.0, 449.0], [267.0, 449.0], [267.0, 537.0], [247.0, 537.0]], [[227.0, 449.0], [248.0, 449.0], [248.0, 519.0], [227.0, 519.0]]], "lines": ["やっぱりなに", "町で何か", "起こってる", "のよ．．．！"]}, {"box": [49, 439, 154, 579], "vertical": true, "font_size": 24, "lines_coords": [[[132.0, 440.0], [154.0, 440.0], [154.0, 498.0], [132.0, 498.0]], [[111.0, 439.0], [138.0, 439.0], [141.0, 533.0], [114.0, 533.0]], [[90.0, 440.0], [111.0, 440.0], [114.0, 579.0], [93.0, 579.0]], [[66.0, 440.0], [95.0, 439.0], [98.0, 497.0], [69.0, 498.0]], [[50.0, 440.0], [71.0, 440.0], [69.0, 562.0], [49.0, 562.0]]], "lines": ["ああ．．．", "さっきからはっぱくおん", "大砲の爆音だって", "何発も", "聞こえるしな．．．"]}, {"box": [651, 825, 678, 934], "vertical": true, "font_size": 27, "lines_coords": [[[651.0, 827.0], [678.0, 827.0], [678.0, 932.0], [651.0, 932.0]]], "lines": ["．．．．．．よし"]}, {"box": [177, 832, 242, 963], "vertical": true, "font_size": 27, "lines_coords": [[[211.0, 832.0], [242.0, 832.0], [242.0, 958.0], [211.0, 958.0]], [[177.0, 832.0], [203.0, 832.0], [203.0, 963.0], [177.0, 963.0]]], "lines": ["わしが町へ", "行ってくる"]}, {"box": [68, 897, 132, 1055], "vertical": true, "font_size": 27, "lines_coords": [[[107.0, 900.0], [132.0, 900.0], [132.0, 1004.0], [107.0, 1004.0]], [[68.0, 897.0], [93.0, 897.0], [93.0, 1055.0], [68.0, 1055.0]]], "lines": ["みんなは", "ここで待て！"]}]}